odoo/addons/document_page_reference_search/README.rst
odoo/addons/document_page_reference_search/__init__.py
odoo/addons/document_page_reference_search/__manifest__.py
odoo/addons/document_page_reference_search/data/parameters.xml
odoo/addons/document_page_reference_search/i18n/document_page_reference_search.pot
odoo/addons/document_page_reference_search/models/__init__.py
odoo/addons/document_page_reference_search/models/document_page.py
odoo/addons/document_page_reference_search/models/document_page_reference_rule.py
odoo/addons/document_page_reference_search/readme/CONTRIBUTORS.rst
odoo/addons/document_page_reference_search/readme/DESCRIPTION.rst
odoo/addons/document_page_reference_search/readme/USAGE.rst
odoo/addons/document_page_reference_search/security/ir.model.access.csv
odoo/addons/document_page_reference_search/static/description/icon.png
odoo/addons/document_page_reference_search/static/description/index.html
odoo/addons/document_page_reference_search/tests/__init__.py
odoo/addons/document_page_reference_search/tests/test_document_page_reference_search.py
odoo/addons/document_page_reference_search/views/document_page_reference_rule.xml
odoo11_addon_document_page_reference_search-11.0.1.0.0.99.dev3.dist-info/METADATA
odoo11_addon_document_page_reference_search-11.0.1.0.0.99.dev3.dist-info/WHEEL
odoo11_addon_document_page_reference_search-11.0.1.0.0.99.dev3.dist-info/top_level.txt
odoo11_addon_document_page_reference_search-11.0.1.0.0.99.dev3.dist-info/RECORD
